prefect_cloud/__init__.py
prefect_cloud/auth.py
prefect_cloud/client.py
prefect_cloud/dependencies.py
prefect_cloud/deployments.py
prefect_cloud/following.py
prefect_cloud/github.py
prefect_cloud/py.typed
prefect_cloud/py_versions.py
prefect_cloud/settings.py
prefect_cloud/types.py
prefect_cloud/cli/__init__.py
prefect_cloud/cli/auth.py
prefect_cloud/cli/completions.py
prefect_cloud/cli/deployments.py
prefect_cloud/cli/github.py
prefect_cloud/cli/root.py
prefect_cloud/cli/utilities.py
prefect_cloud/schemas/__init__.py
prefect_cloud/schemas/actions.py
prefect_cloud/schemas/objects.py
prefect_cloud/schemas/responses.py
prefect_cloud/utilities/__init__.py
prefect_cloud/utilities/blocks.py
prefect_cloud/utilities/callables.py
prefect_cloud/utilities/callback.py
prefect_cloud/utilities/exception.py
prefect_cloud/utilities/flows.py
prefect_cloud/utilities/generics.py
prefect_cloud/utilities/tui.py
prefect_cloud/utilities/urls.py
prefect_cloud-0.1.9.dist-info/METADATA
prefect_cloud-0.1.9.dist-info/WHEEL
prefect_cloud-0.1.9.dist-info/entry_points.txt
prefect_cloud-0.1.9.dist-info/licenses/LICENSE
prefect_cloud-0.1.9.dist-info/RECORD
