Metadata-Version: 2.4
Name: prefect-cloud
Version: 0.1.9
Summary: Package for easily deploying to Prefect Cloud.
Author-email: "Prefect Technologies, Inc." <help@prefect.io>
License-File: LICENSE
Requires-Python: >=3.10
Requires-Dist: cachetools>=6.0.0
Requires-Dist: croniter>=6.0.0
Requires-Dist: griffe>=1.5.6
Requires-Dist: httpx>=0.28.1
Requires-Dist: pydantic-extra-types>=2.10.2
Requires-Dist: pydantic-settings>=2.7.1
Requires-Dist: pydantic>=2.10.6
Requires-Dist: readchar>=4.2.1
Requires-Dist: rich>=13.9.4
Requires-Dist: toml>=0.10.2
Requires-Dist: typer>=0.13.1
Requires-Dist: typing-extensions>=4.12.2
Requires-Dist: tzlocal>=5.2
Requires-Dist: uv>=0.5.26
Requires-Dist: websockets>=13.0
